README.txt
setup.cfg
setup.py
TGPaginate.egg-info/PKG-INFO
TGPaginate.egg-info/SOURCES.txt
TGPaginate.egg-info/dependency_links.txt
TGPaginate.egg-info/entry_points.txt
TGPaginate.egg-info/not-zip-safe
TGPaginate.egg-info/requires.txt
TGPaginate.egg-info/top_level.txt
tgpaginate/__init__.py
tgpaginate/controllers.py
tgpaginate/release.py
tgpaginate/widgets.py
tgpaginate/static/css/paginatedgrid.css
tgpaginate/static/images/spinner.gif
tgpaginate/static/javascript/paginatedajaxgrid.js
tgpaginate/static/javascript/paginatedajaxgrid.min.js
tgpaginate/templates/__init__.py
tgpaginate/templates/paginatedajaxgrid.kid
tgpaginate/templates/paginatedgrid.kid